biaoshu_hpc/__init__.py
biaoshu_hpc/difflib_hpc/__init__.py
biaoshu_hpc/difflib_hpc/difflib_hpc.py
biaoshu_hpc/difflib_hpc/longest_common_substring.cpython-311-aarch64-linux-gnu.so
biaoshu_hpc/difflib_hpc/longest_common_substring.cpython-311-x86_64-linux-gnu.so
biaoshu_hpc/lcs/__init__.py
biaoshu_hpc/lcs/lsc.py
biaoshu_hpc/lcs/telehpc.cp310-win_amd64.pyd
biaoshu_hpc/lcs/telehpc.cp311-win_amd64.pyd
biaoshu_hpc/lcs/telehpc.cpython-310-aarch64-linux-gnu.so
biaoshu_hpc/lcs/telehpc.cpython-310-x86_64-linux-gnu.so
biaoshu_hpc/lcs/telehpc.cpython-311-aarch64-linux-gnu.so
biaoshu_hpc/lcs/telehpc.cpython-311-x86_64-linux-gnu.so
biaoshu_hpc-0.1.26.dist-info/METADATA
biaoshu_hpc-0.1.26.dist-info/WHEEL
biaoshu_hpc-0.1.26.dist-info/top_level.txt
biaoshu_hpc-0.1.26.dist-info/RECORD
