Metadata-Version: 2.1
Name: biaoshu-hpc
Version: 0.1.26
Summary: biaoshu_hpc
Author: huangwenbin
Author-email: huangwb5@chinatelecom.cn 
Classifier: Development Status :: 4 - Beta
Classifier: Intended Audience :: Developers
Classifier: License :: OSI Approved :: MIT License
Classifier: Programming Language :: Python :: 3
Classifier: Programming Language :: Python :: 3.10
Requires-Python: >=3.10
